ZeroToHero2017NianJiqiZhixinAiGaofenGaishuWenzhangQuanji/README.md
ZeroToHero2017NianJiqiZhixinAiGaofenGaishuWenzhangQuanji/__init__.py
ZeroToHero2017NianJiqiZhixinAiGaofenGaishuWenzhangQuanji/__main__.py
ZeroToHero2017NianJiqiZhixinAiGaofenGaishuWenzhangQuanji/file.epub
ZeroToHero2017NianJiqiZhixinAiGaofenGaishuWenzhangQuanji/index.html
ZeroToHero2017NianJiqiZhixinAiGaofenGaishuWenzhangQuanji/css/__init__.py
ZeroToHero2017NianJiqiZhixinAiGaofenGaishuWenzhangQuanji/css/annotations.css
ZeroToHero2017NianJiqiZhixinAiGaofenGaishuWenzhangQuanji/css/main.css
ZeroToHero2017NianJiqiZhixinAiGaofenGaishuWenzhangQuanji/css/normalize.css
ZeroToHero2017NianJiqiZhixinAiGaofenGaishuWenzhangQuanji/css/popup.css
ZeroToHero2017NianJiqiZhixinAiGaofenGaishuWenzhangQuanji/font/__init__.py
ZeroToHero2017NianJiqiZhixinAiGaofenGaishuWenzhangQuanji/font/fontello.eot
ZeroToHero2017NianJiqiZhixinAiGaofenGaishuWenzhangQuanji/font/fontello.svg
ZeroToHero2017NianJiqiZhixinAiGaofenGaishuWenzhangQuanji/font/fontello.ttf
ZeroToHero2017NianJiqiZhixinAiGaofenGaishuWenzhangQuanji/font/fontello.woff
ZeroToHero2017NianJiqiZhixinAiGaofenGaishuWenzhangQuanji/img/__init__.py
ZeroToHero2017NianJiqiZhixinAiGaofenGaishuWenzhangQuanji/img/annotator-glyph-sprite.png
ZeroToHero2017NianJiqiZhixinAiGaofenGaishuWenzhangQuanji/img/annotator-icon-sprite.png
ZeroToHero2017NianJiqiZhixinAiGaofenGaishuWenzhangQuanji/img/apple-touch-icon.png
ZeroToHero2017NianJiqiZhixinAiGaofenGaishuWenzhangQuanji/img/cancelfullscreen.png
ZeroToHero2017NianJiqiZhixinAiGaofenGaishuWenzhangQuanji/img/close.png
ZeroToHero2017NianJiqiZhixinAiGaofenGaishuWenzhangQuanji/img/fullscreen.png
ZeroToHero2017NianJiqiZhixinAiGaofenGaishuWenzhangQuanji/img/loader.gif
ZeroToHero2017NianJiqiZhixinAiGaofenGaishuWenzhangQuanji/img/menu-icon.png
ZeroToHero2017NianJiqiZhixinAiGaofenGaishuWenzhangQuanji/img/save.png
ZeroToHero2017NianJiqiZhixinAiGaofenGaishuWenzhangQuanji/img/saved.png
zero_to_hero_2017_nian_jiqi_zhixin_ai_gaofen_gaishu_wenzhang_quanji-2024.3.3.0.dist-info/METADATA
zero_to_hero_2017_nian_jiqi_zhixin_ai_gaofen_gaishu_wenzhang_quanji-2024.3.3.0.dist-info/WHEEL
zero_to_hero_2017_nian_jiqi_zhixin_ai_gaofen_gaishu_wenzhang_quanji-2024.3.3.0.dist-info/entry_points.txt
zero_to_hero_2017_nian_jiqi_zhixin_ai_gaofen_gaishu_wenzhang_quanji-2024.3.3.0.dist-info/top_level.txt
zero_to_hero_2017_nian_jiqi_zhixin_ai_gaofen_gaishu_wenzhang_quanji-2024.3.3.0.dist-info/RECORD
